package_DEIDARA285231/__init__.py
package_DEIDARA285231/agent.py
package_DEIDARA285231/convert.py
package_DEIDARA285231/firestore_client_singleton.py
GroupChatAgent-0.0.0.dist-info/LICENSE.md
GroupChatAgent-0.0.0.dist-info/METADATA
GroupChatAgent-0.0.0.dist-info/WHEEL
GroupChatAgent-0.0.0.dist-info/top_level.txt
GroupChatAgent-0.0.0.dist-info/RECORD
